README.md
setup.cfg
setup.py
bunk_py/__init__.py
bunk_py/bunk_py.py
bunk_py.egg-info/PKG-INFO
bunk_py.egg-info/SOURCES.txt
bunk_py.egg-info/dependency_links.txt
bunk_py.egg-info/requires.txt
bunk_py.egg-info/top_level.txt