Metadata-Version: 1.1
Name: bunk-py
Version: 2.3.1
Summary: An API wrapper for BunkServices API.
Home-page: https://github.com/DaWinnerIsHere/bunk_py
Author: DaWinnerIsHere
Author-email: dawinnerishere@gmail.com
License: UNKNOWN
Download-URL: https://github.com/DaWinnerIsHere/bunk_py/archive/refs/tags/2.3.1.tar.gz
Platform: UNKNOWN
